{
  "level":{
    "level":1,
	"name":"The beginning",
	"intro_story":null
	},
  "items":[
    "Dagger",
	"LightArmour",
	"Dagger",
	"Rock",
	"LightArmour"],
  "enemies":[
    "Goblin",
	"Kobold",
	"Kobold"],
  "rooms":[
    {
	  "tile":"StartingRoom",
	  "kwargs":{
	    "x":0,
	    "y":0
	  }
	},
	{
	  "tile":"LootRoom",
	  "kwargs":{
	    "x":1,
	    "y":0
	  }
	},
	{
	  "tile":"EmptyRoom",
	  "kwargs":{
	    "x":2,
	    "y":0
	  }
	},
    {
	  "tile":"LootRoom",
	  "kwargs":{
	    "intro_text":"You see a small key on the floor.  Pick it up?",
	    "x":3,
	    "y":0,
	    "item":"DungeonKey",
		"is_trap":false
	  }
	},
	{
	  "tile":"EmptyRoom",
	  "kwargs":{
	    "x":0,
	    "y":1
	  }
	},
	{
	  "tile":"LootRoom",
	  "kwargs":{
	    "x":0,
	    "y":2
	  }
	},
	{
	  "tile":"EnemyRoom",
	  "kwargs":{
	    "x":1,
	    "y":2,
		"enemy":null,
		"is_trap":false
	  }
	},
	{
	  "tile":"EmptyRoom",
	  "kwargs":{
	    "x":2,
	    "y":2
	  }
	},
	{
	  "tile":"DungeonEnd",
	  "kwargs":{
	    "x":3,
	    "y":2
	  }
	}
  ]
}
	